analitiks/__init__.py
analitiks/connection_utils.py
analitiks/logger_utils.py
analitiks/tg_bot_checklist.py
analitiks/tg_bot_path.py
analitiks-1.0.9.dist-info/METADATA
analitiks-1.0.9.dist-info/WHEEL
analitiks-1.0.9.dist-info/top_level.txt
analitiks-1.0.9.dist-info/RECORD
