Metadata-Version: 2.4
Name: analitiks
Version: 1.0.9
Summary: Библиотека для Аналитика
Author: DREAM
Author-email: dream9565@mail.ru
Classifier: Programming Language :: Python :: 3
Classifier: License :: OSI Approved :: MIT License
Classifier: Operating System :: OS Independent
Requires-Python: >=3.6
Requires-Dist: psycopg2-binary
Requires-Dist: sqlalchemy
Requires-Dist: telebot
Requires-Dist: requests
Requires-Dist: openpyxl
Requires-Dist: numpy
Requires-Dist: pandas
Requires-Dist: matplotlib
Requires-Dist: seaborn
Requires-Dist: xlrd
Requires-Dist: xlwt
Requires-Dist: pymysql
Dynamic: author
Dynamic: author-email
Dynamic: classifier
Dynamic: description
Dynamic: description-content-type
Dynamic: requires-dist
Dynamic: requires-python
Dynamic: summary
